pyfase.py
pyfase-1.0.5.dist-info/LICENSE
pyfase-1.0.5.dist-info/METADATA
pyfase-1.0.5.dist-info/WHEEL
pyfase-1.0.5.dist-info/top_level.txt
pyfase-1.0.5.dist-info/RECORD
