Metadata-Version: 2.1
Name: pyfase
Version: 1.0.5
Summary: A Fast-Asynchronous-microService-Environment based on ZeroMQ.
Home-page: https://github.com/jomorais/pyfase
Author: Joaci Morais
Author-email: joaci.morais@gmail.com
License: GPLv3
Platform: any
Classifier: Programming Language :: Python
Classifier: Programming Language :: Python :: 2.7
Classifier: Programming Language :: Python :: 3.4
Classifier: Programming Language :: Python :: 3.5
Classifier: Programming Language :: Python :: Implementation
Classifier: Topic :: Software Development :: Libraries
Classifier: Topic :: System :: Distributed Computing
Classifier: Topic :: System :: Networking
License-File: LICENSE
Requires-Dist: zmq
